LICENSE.txt
MANIFEST.in
README.rst
clean_instances.sh
sample_config.yml
setup.py
start_instances.sh
mongopool/__init__.py
mongopool/mongopool.py
mongopool.egg-info/PKG-INFO
mongopool.egg-info/SOURCES.txt
mongopool.egg-info/dependency_links.txt
mongopool.egg-info/requires.txt
mongopool.egg-info/top_level.txt