Metadata-Version: 1.1
Name: mongopool
Version: 0.2
Summary: The tool that keeps all your mongos in one place
Home-page: http://github.com/ubervu/mongopool/
Author: UberVU
Author-email: development@ubervu.com
License: Apache Software License
Platform: any
Classifier: Development Status :: 4 - Beta
Classifier: Environment :: Web Environment
Classifier: Intended Audience :: Developers
Classifier: License :: OSI Approved :: Apache Software License
Classifier: Natural Language :: English
Classifier: Operating System :: OS Independent
Classifier: Programming Language :: Python
Classifier: Topic :: Database
Classifier: Topic :: Software Development :: Libraries :: Python Modules
